andhrica/__init__.py
andhrica/devanagari_hindi.py
andhrica/devanagari_sanskrit.py
andhrica/gondi.py
andhrica/kannada.py
andhrica/malayalam.py
andhrica/odia.py
andhrica/progress.py
andhrica/tamil.py
andhrica/telugu.py
andhrica-0.1.0.dist-info/licenses/LICENSE
andhrica-0.1.0.dist-info/METADATA
andhrica-0.1.0.dist-info/WHEEL
andhrica-0.1.0.dist-info/top_level.txt
andhrica-0.1.0.dist-info/RECORD
