Metadata-Version: 2.4
Name: andhrica
Version: 0.1.0
Summary: Fast ISO 15919 transliteration for Indic scripts
Author: neet2407
License: MIT
Project-URL: Homepage, https://github.com/neet2407/andhrica
Project-URL: Repository, https://github.com/neet2407/andhrica
Project-URL: Issues, https://github.com/neet2407/andhrica/issues
Keywords: transliteration,indic,telugu,tamil,malayalam,kannada,hindi,sanskrit,iso-15919,nlp
Classifier: Development Status :: 4 - Beta
Classifier: Intended Audience :: Developers
Classifier: Intended Audience :: Science/Research
Classifier: License :: OSI Approved :: MIT License
Classifier: Programming Language :: Python :: 3
Classifier: Programming Language :: Python :: 3.10
Classifier: Programming Language :: Python :: 3.11
Classifier: Programming Language :: Python :: 3.12
Classifier: Topic :: Text Processing :: Linguistic
Requires-Python: >=3.10
License-File: LICENSE
Dynamic: license-file
